illdata/__init__.py
illdata/cli.py
illdata/exceptions.py
illdata/sftp.py
illdata-0.2.1.dist-info/licenses/LICENSE
illdata-0.2.1.dist-info/METADATA
illdata-0.2.1.dist-info/WHEEL
illdata-0.2.1.dist-info/entry_points.txt
illdata-0.2.1.dist-info/top_level.txt
illdata-0.2.1.dist-info/RECORD
