Metadata-Version: 2.4
Name: illdata
Version: 0.2.1
Summary: Python client for downloading data from Institute Laue Langevin via SFTP.
Author: Petr Čermák
Project-URL: Repository, https://github.com/me2d09/ILLData
Keywords: ILL,SFTP,data
Classifier: Programming Language :: Python :: 3
Classifier: License :: OSI Approved :: MIT License
Classifier: Operating System :: OS Independent
Classifier: Environment :: Console
Classifier: Topic :: Internet :: File Transfer Protocol (FTP)
Classifier: Topic :: Utilities
Requires-Python: >=3.8
License-File: LICENSE
Requires-Dist: paramiko>=3.0
Dynamic: license-file
